django_jeaves-0.1.dist-info/DESCRIPTION.rst
django_jeaves-0.1.dist-info/METADATA
django_jeaves-0.1.dist-info/RECORD
django_jeaves-0.1.dist-info/WHEEL
django_jeaves-0.1.dist-info/metadata.json
django_jeaves-0.1.dist-info/top_level.txt
jeaves/__init__.py
jeaves/admin.py
jeaves/apps.py
jeaves/models.py
jeaves/tests.py
jeaves/views.py
