Metadata-Version: 2.0
Name: django-jeaves
Version: 0.1
Summary: Django EAV using JSONField
Home-page: https://github.com/zostera/django-jeaves/
Author: Dylan Verheul
Author-email: dylan@zostera.nl
License: MIT
Platform: UNKNOWN
Requires-Dist: Django (>=1.11)
